franz/__init__.py
franz/miniclient/__init__.py
franz/miniclient/agjson.py
franz/miniclient/repository.py
franz/miniclient/request.py
franz/miniclient/test.py
franz/miniclient/backends/__init__.py
franz/miniclient/backends/requests.py
franz/openrdf/__init__.py
franz/openrdf/connect.py
franz/openrdf/exceptions.py
franz/openrdf/model/__init__.py
franz/openrdf/model/literal.py
franz/openrdf/model/statement.py
franz/openrdf/model/utils.py
franz/openrdf/model/value.py
franz/openrdf/model/valuefactory.py
franz/openrdf/query/__init__.py
franz/openrdf/query/dataset.py
franz/openrdf/query/pandas_support.py
franz/openrdf/query/query.py
franz/openrdf/query/queryresult.py
franz/openrdf/query/repositoryresult.py
franz/openrdf/repository/__init__.py
franz/openrdf/repository/attributes.py
franz/openrdf/repository/repository.py
franz/openrdf/repository/repositoryconnection.py
franz/openrdf/repository/repositoryresult.py
franz/openrdf/repository/transactions.py
franz/openrdf/rio/__init__.py
franz/openrdf/rio/docformat.py
franz/openrdf/rio/formats.py
franz/openrdf/rio/rdfformat.py
franz/openrdf/rio/rdfwriter.py
franz/openrdf/rio/rdfxmlwriter.py
franz/openrdf/rio/tupleformat.py
franz/openrdf/sail/__init__.py
franz/openrdf/sail/allegrographserver.py
franz/openrdf/sail/spec.py
franz/openrdf/tests/__init__.py
franz/openrdf/tests/conftest.py
franz/openrdf/tests/importtests.py
franz/openrdf/tests/kennedy-error.nt
franz/openrdf/tests/kennedy.ntriples
franz/openrdf/tests/kennedy.ttl
franz/openrdf/tests/kennedy.ttl.gz
franz/openrdf/tests/lesmis.rdf
franz/openrdf/tests/newtests.py
franz/openrdf/tests/nlq_test.py
franz/openrdf/tests/nsw.ttl
franz/openrdf/tests/rdfstar_tests.py
franz/openrdf/tests/relative_rules.txt
franz/openrdf/tests/ssl-dir.sh
franz/openrdf/tests/test_pandas_support.py
franz/openrdf/tests/tests.py
franz/openrdf/tests/trig-star.trig
franz/openrdf/tests/triplesbuffer_tests.py
franz/openrdf/tests/turtle-star.ttls
franz/openrdf/tests/tz.py
franz/openrdf/tests/vc-db-1.rdf
agraph_python-104.3.0.dist-info/METADATA
agraph_python-104.3.0.dist-info/WHEEL
agraph_python-104.3.0.dist-info/licenses/LICENSE
agraph_python-104.3.0.dist-info/RECORD
