Metadata-Version: 2.4
Name: agraph-python
Version: 104.3.0
Summary: AllegroGraph Python client
Project-URL: homepage, https://github.com/franzinc/agraph-python
Project-URL: documentation, https://franz.com/agraph/support/documentation/current/python/
Project-URL: repository, https://github.com/franzinc/agraph-python
Project-URL: changelog, https://franz.com/agraph/support/documentation/current/python/changes.html
Author-email: "Franz Inc." <support@franz.com>
License: Copyright (c) Franz Inc.  Lafayette, CA 94549
License-File: LICENSE
Classifier: Development Status :: 5 - Production/Stable
Classifier: Intended Audience :: Developers
Classifier: License :: OSI Approved :: MIT License
Classifier: Operating System :: OS Independent
Classifier: Programming Language :: Python
Classifier: Programming Language :: Python :: 3
Classifier: Programming Language :: Python :: 3 :: Only
Classifier: Programming Language :: Python :: 3.8
Classifier: Programming Language :: Python :: 3.9
Classifier: Programming Language :: Python :: 3.10
Classifier: Programming Language :: Python :: 3.11
Classifier: Programming Language :: Python :: 3.12
Classifier: Programming Language :: Python :: 3.13
Classifier: Topic :: Database
Classifier: Topic :: Software Development :: Libraries
Classifier: Topic :: Software Development :: Libraries :: Python Modules
Requires-Python: <3.14,>=3.8
Requires-Dist: iso8601<2.2.0,>=2.1.0
Requires-Dist: pandas<3.0.0,>=2.0.0
Requires-Dist: requests[socks]==2.32.4
Provides-Extra: dev
Requires-Dist: black~=23.3.0; extra == 'dev'
Requires-Dist: ipython~=7.34.0; extra == 'dev'
Requires-Dist: isort~=5.11.0; extra == 'dev'
Requires-Dist: packaging<23.3.0,>=23.2.0; extra == 'dev'
Requires-Dist: pytest-mock~=3.11.0; extra == 'dev'
Requires-Dist: pytest-timeout~=2.2.0; extra == 'dev'
Requires-Dist: pytest~=7.0.0; extra == 'dev'
Requires-Dist: sphinxcontrib-jupyter~=0.5.0; extra == 'dev'
Provides-Extra: docs
Requires-Dist: sphinxcontrib-jupyter~=0.5.0; extra == 'docs'
Provides-Extra: style
Requires-Dist: black~=23.3.0; extra == 'style'
Requires-Dist: isort~=5.11.0; extra == 'style'
Provides-Extra: test
Requires-Dist: packaging<23.3.0,>=23.2.0; extra == 'test'
Requires-Dist: pytest-mock~=3.11.0; extra == 'test'
Requires-Dist: pytest-timeout~=2.2.0; extra == 'test'
Requires-Dist: pytest~=7.0.0; extra == 'test'
